ppfl/__init__.py
ppfl/__main__.py
ppfl-1.0.0.dist-info/LICENSE
ppfl-1.0.0.dist-info/METADATA
ppfl-1.0.0.dist-info/WHEEL
ppfl-1.0.0.dist-info/entry_points.txt
ppfl-1.0.0.dist-info/top_level.txt
ppfl-1.0.0.dist-info/RECORD
